[
  {
    "id": "uband",
    "entity": "Band Protocol",
    "name": "Band Protocol",
    "symbol": "BAND",
    "decimals": "6",
    "type": "native",
    "total_supply_api": "https://api.bandchain.org/supply/total",
    "circ_supply_api": "https://api.bandchain.org/supply/circulating",
    "icon": "https://raw.githubusercontent.com/cosmos/chain-registry/master/bandchain/images/band.svg",
    "coinmarketcap": "https://coinmarketcap.com/currencies/band-protocol/",
    "coingecko": "https://www.coingecko.com/en/coins/band-protocol"
  },
  {
    "id": "ibc/6B8531505147C9FF2AC90BC096AEC5D8E77EE3582874640FA5FE4E4FB382D2AC",
    "entity": "Osmosis",
    "name": "Osmosis",
    "symbol": "OSMO",
    "decimals": "6",
    "type": "ibc",
    "circ_supply_api": "https://rest.cosmos.directory/osmosis/cosmos/bank/v1beta1/supply?pagination.key=dW9zbW8%3D&pagination.limit=1",
    "total_supply_api": "https://rest.cosmos.directory/osmosis/cosmos/bank/v1beta1/supply?pagination.key=dW9zbW8%3D&pagination.limit=1",
    "icon": "https://raw.githubusercontent.com/cosmos/chain-registry/master/osmosis/images/osmo.svg",
    "coinmarketcap": "https://coinmarketcap.com/currencies/osmosis",
    "coingecko": "https://www.coingecko.com/en/coins/osmosis"
  }
]
